rfswarm_manager/__init__.py
rfswarm_manager/rfswarm.py
rfswarm_manager/icons/rfswarm-logo-128.ico
rfswarm_manager/icons/rfswarm-logo-128.png
rfswarm_manager/icons/rfswarm-manager-1024.png
rfswarm_manager/icons/rfswarm-manager-128.ico
rfswarm_manager/icons/rfswarm-manager-128.png
rfswarm_manager-1.5.3.data/data/rfswarm_manager/icons/rfswarm-logo-128.ico
rfswarm_manager-1.5.3.data/data/rfswarm_manager/icons/rfswarm-logo-128.png
rfswarm_manager-1.5.3.data/data/rfswarm_manager/icons/rfswarm-manager-1024.png
rfswarm_manager-1.5.3.data/data/rfswarm_manager/icons/rfswarm-manager-128.ico
rfswarm_manager-1.5.3.data/data/rfswarm_manager/icons/rfswarm-manager-128.png
rfswarm_manager-1.5.3.dist-info/licenses/LICENSE
rfswarm_manager-1.5.3.dist-info/METADATA
rfswarm_manager-1.5.3.dist-info/WHEEL
rfswarm_manager-1.5.3.dist-info/entry_points.txt
rfswarm_manager-1.5.3.dist-info/top_level.txt
rfswarm_manager-1.5.3.dist-info/RECORD
